Module_4/Task4/design.sv
// ===== design.sv =====
module nor_realization (
    input  logic a,
    input  logic b,
    input  logic c,
    input  logic d,
    output logic f_orig,
    output logic f_nor
);

    // 1. Direct assignment using the original expression
    assign f_orig = (b | c | d) & (~a | b | c) & (~a | d);

    // 2. Pure NOR assignment using the reduction NOR (~|) operator
    logic a_not, term1, term2, term3;
    
    // a' = a NOR a
    assign a_not = ~|{a, a};        
    
    // Inner NOR terms: (X + Y + Z)'
    assign term1 = ~|{b, c, d};     
    assign term2 = ~|{a_not, b, c}; 
    assign term3 = ~|{a_not, d};    
    
    // Outer NOR operation combining the terms
    assign f_nor = ~|{term1, term2, term3}; 

endmodule

Module_4/Task4/testbench.sv
// ===== testbench.sv =====
module tb;
    logic a, b, c, d;
    logic f_orig, f_nor;

    // Use an integer to prevent infinite loop overflow
    int abcd; 

    // Instantiate the design module
    nor_realization dut (
        .a(a), 
        .b(b), 
        .c(c), 
        .d(d), 
        .f_orig(f_orig), 
        .f_nor(f_nor)
    );

    // Self-checking task
    task automatic check(input logic actual, expected, string name);
        if (actual !== expected)
            $display("[FAIL] %s: expected=%0b actual=%0b", name, expected, actual);
        else
            $display("[PASS] %s: value=%0b", name, actual);
    endtask

    initial begin
        $dumpfile("dump.vcd");
        $dumpvars(0, tb);

        $display("--- Testing NOR-Only Realization ---");
        
        // Exhaustively test all 16 combinations (2^4)
        for (abcd = 0; abcd <= 15; abcd = abcd + 1) begin
            // SystemVerilog extracts the bottom 4 bits of the integer
            {a, b, c, d} = abcd; 
            
            #10; // Allow combinational logic to settle
            
            // Check if the NOR implementation perfectly matches the original
            check(f_nor, f_orig, $sformatf("Match check for a=%0b, b=%0b, c=%0b, d=%0b", a, b, c, d));
        end

        $finish;
    end
endmodule

Module_4/Task4/dump.vcd
$date
	Mon Jul 27 20:22:42 2026
$end
$version
	Icarus Verilog
$end
$timescale
	1s
$end
$scope module tb $end
$var wire 1 ! f_orig $end
$var wire 1 " f_nor $end
$var reg 1 # a $end
$var reg 1 $ b $end
$var reg 1 % c $end
$var reg 1 & d $end
$var integer 32 ' abcd [31:0] $end
$scope module dut $end
$var wire 1 # a $end
$var wire 1 $ b $end
$var wire 1 % c $end
$var wire 1 & d $end
$var wire 1 ! f_orig $end
$var wire 1 ( term3 $end
$var wire 1 ) term2 $end
$var wire 1 * term1 $end
$var wire 1 " f_nor $end
$var wire 1 + a_not $end
$upscope $end
$scope task check $end
$upscope $end
$upscope $end
$enddefinitions $end
$comment Show the parameter values. $end
$dumpall
$end
#0
$dumpvars
1+
1*
0)
0(
b0 '
0&
0%
0$
0#
0"
0!
$end
#10
1!
1"
0*
1&
b1 '
#20
1!
1%
1"
0*
0&
b10 '
#30
1&
b11 '
#40
1$
1"
0*
0%
0&
b100 '
#50
1&
b101 '
#60
1%
0&
b110 '
#70
1&
b111 '
#80
0!
1)
1(
0+
1#
0"
1*
0$
0%
0&
b1000 '
#90
0*
0(
1&
b1001 '
#100
0)
1%
0*
1(
0&
b1010 '
#110
1!
1"
0(
1&
b1011 '
#120
0!
1$
0*
0)
0%
0"
1(
0&
b1100 '
#130
1!
1"
0(
1&
b1101 '
#140
0!
1%
0"
1(
0&
b1110 '
#150
1!
1"
0(
1&
b1111 '
#160
b10000 '
