Module_4/Task5/design.sv
// ===== design.sv =====
module parity_generator (
    input  logic [3:0] data,
    output logic       parity
);

    // Reduction XOR operator simplifies the entire vector to 1 bit
    assign parity = ^data;

endmodule

Module_4/Task5/testbench.sv
// ===== testbench.sv =====
module tb;
    logic [3:0] data;
    logic       parity;
    
    // Integer loop variable to prevent infinite loops
    int i; 

    // Instantiate the device under test (DUT)
    parity_generator dut (
        .data(data),
        .parity(parity)
    );

    // Self-checking task pattern
    task automatic check(input logic actual, expected, string name);
        if (actual !== expected)
            $display("[FAIL] %s: expected=%0b actual=%0b", name, expected, actual);
        else
            $display("[PASS] %s: value=%0b", name, actual);
    endtask

    initial begin
        $dumpfile("dump.vcd");
        $dumpvars(0, tb);

        $display("--- Testing 4-bit Parity Generator ---");

        // Sweep all 16 combinations (2^4)
        for (i = 0; i <= 15; i = i + 1) begin
            // Extract the lower 4 bits of the integer loop variable
            data = i; 
            
            #10; // Allow combinational logic to settle
            
            // $countones() returns the number of 1s in the variable.
            // Using modulo 2 (% 2) returns 1 if odd, and 0 if even.
            check(parity, ($countones(data) % 2), $sformatf("Parity of data=%04b", data));
        end

        $finish;
    end
endmodule

Module_4/Task5/dump.vcd
$date
	Mon Jul 27 20:24:07 2026
$end
$version
	Icarus Verilog
$end
$timescale
	1s
$end
$scope module tb $end
$var wire 1 ! parity $end
$var reg 4 " data [3:0] $end
$var integer 32 # i [31:0] $end
$scope module dut $end
$var wire 4 $ data [3:0] $end
$var wire 1 ! parity $end
$upscope $end
$scope task check $end
$upscope $end
$upscope $end
$enddefinitions $end
$comment Show the parameter values. $end
$dumpall
$end
#0
$dumpvars
b0 $
b0 #
b0 "
0!
$end
#10
1!
b1 "
b1 $
b1 #
#20
b10 "
b10 $
b10 #
#30
0!
b11 "
b11 $
b11 #
#40
1!
b100 "
b100 $
b100 #
#50
0!
b101 "
b101 $
b101 #
#60
b110 "
b110 $
b110 #
#70
1!
b111 "
b111 $
b111 #
#80
b1000 "
b1000 $
b1000 #
#90
0!
b1001 "
b1001 $
b1001 #
#100
b1010 "
b1010 $
b1010 #
#110
1!
b1011 "
b1011 $
b1011 #
#120
0!
b1100 "
b1100 $
b1100 #
#130
1!
b1101 "
b1101 $
b1101 #
#140
b1110 "
b1110 $
b1110 #
#150
0!
b1111 "
b1111 $
b1111 #
#160
b10000 #
