Module_4/Task3/design.sv
// ===== design.sv =====

// 1. Half Adder using continuous 'assign'
module half_adder_assign (
    input  logic a,
    input  logic b,
    output logic sum,
    output logic carry
);
    // Dataflow style logic equations
    assign sum   = a ^ b;
    assign carry = a & b;
endmodule

// 2. Half Adder using procedural 'always_comb'
module half_adder_always (
    input  logic a,
    input  logic b,
    output logic sum,
    output logic carry
);
    // Behavioral style using case structure
    always_comb begin
        case ({a, b})
            2'b00: begin sum = 1'b0; carry = 1'b0; end
            2'b01: begin sum = 1'b1; carry = 1'b0; end
            2'b10: begin sum = 1'b1; carry = 1'b0; end
            2'b11: begin sum = 1'b0; carry = 1'b1; end
            // Always include a default branch to prevent inferred latches
            default: begin sum = 1'b0; carry = 1'b0; end 
        endcase
    end
endmodule

// 3. Full Adder using structural composition
module full_adder (
    input  logic a,
    input  logic b,
    input  logic cin,
    output logic sum,
    output logic cout
);
    // Internal wires to connect the blocks
    logic ha1_sum, ha1_carry;
    logic ha2_carry;

    // Instantiate First Half Adder (using the assign version)
    half_adder_assign ha1 (
        .a(a),
        .b(b),
        .sum(ha1_sum),
        .carry(ha1_carry)
    );

    // Instantiate Second Half Adder
    half_adder_assign ha2 (
        .a(ha1_sum),
        .b(cin),
        .sum(sum),
        .carry(ha2_carry)
    );

    // Final OR gate to combine the carry outputs
    assign cout = ha1_carry | ha2_carry;
endmodule

Module_4/Task3/testbench.sv
// ===== testbench.sv =====
module tb;
    // Signals for Half Adders
    logic a, b;
    logic sum_assign, carry_assign;
    logic sum_always, carry_always;
    
    // Signals for Full Adder
    logic cin;
    logic fa_sum, fa_cout;

    // SOLUTION: Changed from 'logic' to 'int' to prevent infinite loop overflow
    int ab;
    int abc;

    // Instantiate Half Adder (assign version)
    half_adder_assign dut_ha_assign (
        .a(a), .b(b), .sum(sum_assign), .carry(carry_assign)
    );

    // Instantiate Half Adder (always_comb version)
    half_adder_always dut_ha_always (
        .a(a), .b(b), .sum(sum_always), .carry(carry_always)
    );

    // Instantiate Full Adder
    full_adder dut_fa (
        .a(a), .b(b), .cin(cin), .sum(fa_sum), .cout(fa_cout)
    );

    // Self-checking task
    task automatic check(input logic actual, expected, string name);
        if (actual !== expected)
            $display("[FAIL] %s: expected=%0b actual=%0b", name, expected, actual);
        else
            $display("[PASS] %s: value=%0b", name, actual);
    endtask

    initial begin
        $dumpfile("dump.vcd");
        $dumpvars(0, tb);

        $display("--- Testing Half Adders (assign vs always_comb) ---");
        // Loop using the integer
        for (ab = 0; ab <= 3; ab = ab + 1) begin
            {a, b} = ab; // SystemVerilog automatically extracts the bottom 2 bits
            #10; // Wait for combinational logic to settle
            
            // Confirm identical outputs from both implementations
            if ({sum_assign, carry_assign} === {sum_always, carry_always})
                $display("[PASS] HA Match for a=%0b, b=%0b -> sum=%0b, carry=%0b", 
                         a, b, sum_assign, carry_assign);
            else
                $display("[FAIL] HA Mismatch for a=%0b, b=%0b!", a, b);
        end

        $display("\n--- Testing Full Adder (Structural Composition) ---");
        // Loop using the integer
        for (abc = 0; abc <= 7; abc = abc + 1) begin
            {a, b, cin} = abc; // Automatically extracts the bottom 3 bits
            #10;
            
            // Expected mathematical logic for a full adder
            check(fa_sum,  (a ^ b ^ cin),                 $sformatf("FA Sum  (a=%0b,b=%0b,cin=%0b)", a, b, cin));
            check(fa_cout, ((a & b) | (b & cin) | (a & cin)), $sformatf("FA Cout (a=%0b,b=%0b,cin=%0b)", a, b, cin));
        end

        $finish;
    end
endmodule

Module_4/Task3/dump.vcd
$date
	Mon Jul 27 20:20:56 2026
$end
$version
	Icarus Verilog
$end
$timescale
	1s
$end
$scope module tb $end
$var wire 1 ! sum_assign $end
$var wire 1 " sum_always $end
$var wire 1 # fa_sum $end
$var wire 1 $ fa_cout $end
$var wire 1 % carry_assign $end
$var wire 1 & carry_always $end
$var reg 1 ' a $end
$var reg 1 ( b $end
$var reg 1 ) cin $end
$var integer 32 * ab [31:0] $end
$var integer 32 + abc [31:0] $end
$scope module dut_fa $end
$var wire 1 ' a $end
$var wire 1 ( b $end
$var wire 1 ) cin $end
$var wire 1 $ cout $end
$var wire 1 # sum $end
$var wire 1 , ha2_carry $end
$var wire 1 - ha1_sum $end
$var wire 1 . ha1_carry $end
$scope module ha1 $end
$var wire 1 ' a $end
$var wire 1 ( b $end
$var wire 1 . carry $end
$var wire 1 - sum $end
$upscope $end
$scope module ha2 $end
$var wire 1 - a $end
$var wire 1 ) b $end
$var wire 1 , carry $end
$var wire 1 # sum $end
$upscope $end
$upscope $end
$scope module dut_ha_always $end
$var wire 1 ' a $end
$var wire 1 ( b $end
$var reg 1 & carry $end
$var reg 1 " sum $end
$upscope $end
$scope module dut_ha_assign $end
$var wire 1 ' a $end
$var wire 1 ( b $end
$var wire 1 % carry $end
$var wire 1 ! sum $end
$upscope $end
$scope task check $end
$upscope $end
$upscope $end
$enddefinitions $end
$comment Show the parameter values. $end
$dumpall
$end
#0
$dumpvars
0.
0-
0,
b0 +
b0 *
x)
0(
0'
0&
0%
0$
x#
0"
0!
$end
#10
x$
x,
1-
1"
1!
1(
b1 *
#20
1'
0(
b10 *
#30
0,
1$
0-
1.
1&
0"
0!
1%
1(
b11 *
#40
0$
0.
0&
0%
0#
0'
0(
0)
b100 *
#50
1#
1)
b1 +
#60
1-
1"
1!
1#
1(
0)
b10 +
#70
1$
0#
1,
1)
b11 +
#80
0$
1#
0,
1'
0(
0)
b100 +
#90
1$
0#
1,
1)
b101 +
#100
0-
1.
1&
0"
0!
1%
0#
0,
1(
0)
b110 +
#110
1#
1)
b111 +
#120
b1000 +
